{
	"info": {
		"_postman_id": "9fe45205-46d7-4d91-b050-3a5147db60d4",
		"name": "Beta Twitter",
		"description": "**All users** in the organization: \n\n* Add new user data\n* Retrieve post users\n* Add new post\n* Add comment",
		"schema": "https://schema.getpostman.com/json/collection/v2.1.0/collection.json"
	},
	"item": [
		{
			"name": "get_all_posts",
			"request": {
				"method": "GET",
				"header": [],
				"url": {
					"raw": "localhost:4567/post_json",
					"host": [
						"localhost"
					],
					"port": "4567",
					"path": [
						"post_json"
					]
				}
			},
			"response": []
		},
		{
			"name": "get_all_users",
			"request": {
				"method": "GET",
				"header": [],
				"url": {
					"raw": "http://localhost:4567/users_json",
					"protocol": "http",
					"host": [
						"localhost"
					],
					"port": "4567",
					"path": [
						"users_json"
					]
				}
			},
			"response": []
		},
		{
			"name": "add_comment_by_idPost",
			"request": {
				"method": "GET",
				"header": [],
				"url": {
					"raw": "http://localhost:4567/post/comment/1",
					"protocol": "http",
					"host": [
						"localhost"
					],
					"port": "4567",
					"path": [
						"post",
						"comment",
						"1"
					]
				}
			},
			"response": []
		},
		{
			"name": "add_hashtag_by_idPost",
			"request": {
				"method": "GET",
				"header": [],
				"url": {
					"raw": "http://localhost:4567/post/add_hashtag/1",
					"protocol": "http",
					"host": [
						"localhost"
					],
					"port": "4567",
					"path": [
						"post",
						"add_hashtag",
						"1"
					]
				}
			},
			"response": []
		},
		{
			"name": "get_form_insert",
			"request": {
				"method": "GET",
				"header": [],
				"url": {
					"raw": "http://localhost:4567/post/new",
					"protocol": "http",
					"host": [
						"localhost"
					],
					"port": "4567",
					"path": [
						"post",
						"new"
					]
				}
			},
			"response": []
		},
		{
			"name": "get_post_by_hashtag",
			"request": {
				"method": "GET",
				"header": [],
				"url": {
					"raw": "http://localhost:4567/post/check1",
					"protocol": "http",
					"host": [
						"localhost"
					],
					"port": "4567",
					"path": [
						"post",
						"check1"
					]
				}
			},
			"response": []
		},
		{
			"name": "New Request",
			"request": {
				"method": "GET",
				"header": [],
				"url": null
			},
			"response": []
		}
	],
	"auth": {
		"type": "apikey",
		"apikey": [
			{
				"key": "value",
				"value": "{{key}}",
				"type": "string"
			},
			{
				"key": "key",
				"value": "user-key",
				"type": "string"
			}
		]
	},
	"event": [
		{
			"listen": "prerequest",
			"script": {
				"type": "text/javascript",
				"exec": [
					""
				]
			}
		},
		{
			"listen": "test",
			"script": {
				"type": "text/javascript",
				"exec": [
					""
				]
			}
		}
	]
}